{
  "id": "OP07-064",
  "name": "Sanji",
  "type": "Character",
  "color": [
    "Purple"
  ],
  "cost": 6,
  "power": 6000,
  "counter": 2000,
  "life": null,
  "attribute": "Strike",
  "subtypes": [
    "Straw Hat Crew"
  ],
  "rarity": "SR",
  "set_id": "OP07",
  "image_id": "OP07-064",
  "effect_text": "If the number of DON!! cards on your field is at least 2 less than the number on your opponent's field, give this card in your hand -3 cost. [Blocker] (After your opponent declares an attack, you may rest this card to make it the new target of the attack.)",
  "keywords": [
    "Blocker"
  ],
  "triggers": [],
  "dsl_status": "pending"
}