{
  "id": "OP03-070",
  "name": "Monkey.D.Luffy (Dash Pack)",
  "type": "Character",
  "color": [
    "Purple"
  ],
  "cost": 6,
  "power": 7000,
  "counter": 0,
  "life": null,
  "attribute": "Strike",
  "subtypes": [
    "Straw Hat Crew"
  ],
  "rarity": "R",
  "set_id": "OP04",
  "image_id": "OP03-070",
  "effect_text": "[On Play] DON!! -1 (You may return the specified number of DON!! cards from your field to your DON!! deck.) You may trash 1 Character card with a cost of 5 from your hand: This Character gains [Rush] during this turn. (This card can attack on the turn in which it is played.)",
  "keywords": [
    "Rush"
  ],
  "triggers": [],
  "dsl_status": "pending"
}