{
  "id": "OP09-005",
  "name": "Silvers Rayleigh (SP)",
  "type": "Character",
  "color": [
    "Red"
  ],
  "cost": 5,
  "power": 6000,
  "counter": 1000,
  "life": null,
  "attribute": "Slash",
  "subtypes": [],
  "rarity": "R",
  "set_id": "OP11",
  "image_id": "OP09-005_p1",
  "effect_text": "[Blocker] (After your opponent declares an attack, you may rest this card to make it the new target of the attack.)\n[On Play] If your opponent has 2 or more Characters with a base power of 5000 or more, draw 2 cards and trash 1 card from your hand.",
  "keywords": [
    "Blocker"
  ],
  "triggers": [],
  "dsl_status": "pending"
}